sparen/PROJECT.txt
sparen/__init__.py
sparen/sparen.py
sparen/sparen_draw.py
sparen-0.2.5.dist-info/LICENSE
sparen-0.2.5.dist-info/METADATA
sparen-0.2.5.dist-info/WHEEL
sparen-0.2.5.dist-info/top_level.txt
sparen-0.2.5.dist-info/RECORD
