Metadata-Version: 2.1
Name: sparen
Version: 0.2.5
Summary: A generic logger
Home-page: https://github.com/wheresjames/sparen
Author: Robert Umbehant
Author-email: sparen@wheresjames.com
License: MIT
Platform: UNKNOWN
